kiwitcms_trackers_integration-1.2.1.dist-info/licenses/LICENSE
tcms_settings_dir/__init__.py
tcms_settings_dir/trackers_integration.py
trackers_integration/__init__.py
trackers_integration/admin.py
trackers_integration/auth.py
trackers_integration/menu.py
trackers_integration/models.py
trackers_integration/urls.py
trackers_integration/issuetracker/__init__.py
trackers_integration/issuetracker/mantis.py
trackers_integration/issuetracker/openproject.py
trackers_integration/issuetracker/trac.py
trackers_integration/locale/en/LC_MESSAGES/django.po
trackers_integration/migrations/0001_add_apitoken_model.py
trackers_integration/migrations/__init__.py
kiwitcms_trackers_integration-1.2.1.dist-info/METADATA
kiwitcms_trackers_integration-1.2.1.dist-info/WHEEL
kiwitcms_trackers_integration-1.2.1.dist-info/entry_points.txt
kiwitcms_trackers_integration-1.2.1.dist-info/top_level.txt
kiwitcms_trackers_integration-1.2.1.dist-info/RECORD
