Metadata-Version: 2.4
Name: kiwitcms-trackers-integration
Version: 1.2.1
Summary: Integration between Kiwi TCMS and various Issue Trackers
Home-page: https://github.com/kiwitcms/trackers-integration/
Author: Kiwi TCMS
Author-email: info@kiwitcms.org
License: AGPLv3+
Classifier: Framework :: Django
Classifier: Development Status :: 5 - Production/Stable
Classifier: Topic :: Software Development :: Quality Assurance
Classifier: Topic :: Software Development :: Testing
Classifier: Environment :: Web Environment
Classifier: Intended Audience :: Developers
Classifier: License :: OSI Approved :: GNU Affero General Public License v3 or later (AGPLv3+)
Classifier: Programming Language :: Python :: 3
Classifier: Programming Language :: Python :: 3.8
Classifier: Programming Language :: Python :: 3.9
Classifier: Programming Language :: Python :: 3.11
License-File: LICENSE
Dynamic: author
Dynamic: author-email
Dynamic: classifier
Dynamic: description
Dynamic: home-page
Dynamic: license
Dynamic: license-file
Dynamic: summary
